hb/__init__.py
hacklebox-0.0.0.dist-info/METADATA
hacklebox-0.0.0.dist-info/WHEEL
hacklebox-0.0.0.dist-info/top_level.txt
hacklebox-0.0.0.dist-info/RECORD
