Metadata-Version: 2.1
Name: hacklebox
Version: 0.0.0
Summary: An assortment of utilities
Home-page: UNKNOWN
License: UNKNOWN
Platform: UNKNOWN
